{"person": {"personID": "38108", "FullName": "Bob Johnson", "FirstName": "Bob", "LastName": "Johnson", "publication": [{"title": "Object-Oriented Programming and Protected Objects in Ada 95", "year": "2000", "authors": "Andy J. Wellings,Bob Johnson,Bo Sanden,Jorg Kienzle,Thomas Wolf,Stephen Michell", "jconf": "Ada-Europe", "id": "25705", "label": "0", "organization": "null"}, {"title": "UNIX Metrics: Is The Data In Open Systems The Same From Platform To Platform?", "year": "1995", "authors": "Bob Johnson", "jconf": "Int. CMG Conference", "id": "101675", "label": "1", "organization": "null"}, {"title": "Triad Of Computing In The 21st Century Or, Back To The Future Again", "year": "1995", "authors": "Bob Johnson", "jconf": "Int. CMG Conference", "id": "101676", "label": "1", "organization": "null"}, {"title": "User-centeredness, situatedness, and designing the media of computer documentation", "year": "1990", "authors": "Bob Johnson", "jconf": "SIGDOC", "id": "592593", "label": "2", "organization": "Miami University of Ohio"}, {"title": "Introduction to commentaries on 'Spurious Coin: A History of Science, Management, and Technical Writing' by Bernadette Longo", "year": "2001", "authors": "Bob Johnson", "jconf": "ACM Journal of Computer Documentation", "id": "965379", "label": "3", "organization": "Michigan Technological University"}, {"title": "Manager: The Project Scoping Gamble", "year": "1997", "authors": "Brian Lawrence,Bob Johnson", "jconf": "IEEE Software", "id": "1071125", "label": "4", "organization": "null"}, {"title": "Integrating object-oriented programming and protected objects in Ada 95", "year": "2000", "authors": "Andy J. Wellings,Bob Johnson,Bo Sanden,Jorg Kienzle,Thomas Wolf,Stephen Michell", "jconf": "ACM Trans. Program. Lang. Syst.", "id": "1123975", "label": "0", "organization": "null"}, {"title": "Testing Applications on the Web: Test Planning for Mobile and Internet-Based Systems, 2 edition", "year": "2002", "authors": "Hung Quoc Nguyen,Bob Johnson,Robert Johnson,Michael Hackett", "jconf": "null", "id": "1420785", "label": "5", "organization": "null"}, {"title": "The Wired Neighborhood: An Extended Multimedia Conversation", "year": "1997", "authors": "Bob Johnson", "jconf": "ACM SIGDOC Asterisk Journal of Computer Documentation", "id": "1534175", "label": "2", "organization": "Miami University, Oxford, OH"}, {"title": "Introduction to the book commentaries", "year": "1998", "authors": "Bob Johnson", "jconf": "ACM SIGDOC Asterisk Journal of Computer Documentation", "id": "1549049", "label": "2", "organization": "Miami University, Oxford, OH"}, {"title": "The cult of ISDN", "year": "1989", "authors": "Bob Johnson", "jconf": "PC/Computing", "id": "1625919", "label": "6", "organization": "null"}]}}