{"person": {"personID": "292499", "FullName": "Hong Xie", "FirstName": "Hong", "LastName": "Xie", "publication": [{"title": "An Efficient Method of Volume Rendering for Medical Slices", "year": "1994", "authors": "Wanqing Li,Hong Xie,Yianni Attikiouzel", "jconf": "ICIP (1)", "id": "319210", "label": "0", "organization": "Dept. of Electr. Electron. Eng., Western Australia Univ., Nedlands, WA"}, {"title": "Application of Weighted Ideal Point Method to Environmental/Economic Load Dispatch", "year": "2005", "authors": "Guoli Zhang,Gengyin Li,Hong Xie,Jianwei Ma", "jconf": "ICMLC", "id": "336488", "label": "1", "organization": "null"}, {"title": "BSP Pro: A Java-Based BSP Performance Profiling System", "year": "1999", "authors": "Weiqun Zheng,Shamim Khan,Hong Xie", "jconf": "ISPAN", "id": "446066", "label": "2", "organization": "Sch. of Inf. Technol., Murdoch Univ., WA"}, {"title": "BSP Performance Analysis and Prediction: Tools and Application", "year": "1999", "authors": "Weiqun Zheng,Shamim Khan,Hong Xie", "jconf": "PaCT", "id": "526028", "label": "2", "organization": "null"}, {"title": "Economic Load Dispatch Based on Hybrid Evolutionary Algorithm and Fuzzy Number Ranking Method", "year": "2006", "authors": "Guoli Zhang,Gengyin Li,Hong Xie,Jianwei Ma", "jconf": "International Journal of Uncertainty, Fuzziness and Knowledge-Based Systems", "id": "921863", "label": "1", "organization": "null"}, {"title": "Analysis of multiple query reformulations on the web: The interactive information retrieval context", "year": "2006", "authors": "Soo Young Rieh,Hong Iris Xie", "jconf": "Inf. Process. Manage.", "id": "936538", "label": "3", "organization": "null"}, {"title": "Supporting ease-of-use and user control: desired features and structure of Web-based online IR systems", "year": "2003", "authors": "Hong (Iris) Xie", "jconf": "Inf. Process. Manage.", "id": "937074", "label": "4", "organization": "null"}, {"title": "Non-segmented Document Clustering Using Self-Organizing Map and Frequent Max Substring Technique.", "year": "2009", "authors": "Todsanai Chumwatana,Kok Wai Wong,Hong Xie", "jconf": "null", "id": "1306566", "label": "2", "organization": "School of Information Technology, Murdoch University, Murdoch 6150"}, {"title": "Blind Source Separation of Temporal Correlated Signals", "year": "2007", "authors": "Bin Xia,Hong Xie", "jconf": "Proceedings of the 2007 Third International IEEE Conference on Signal-Image Technologies and Internet-Based System", "id": "1595438", "label": "5", "organization": "null"}, {"title": "Cagr;ohgr;macr;solutions of a class of nonlinear degenerate elliptic systems arising in the thermistor problem", "year": "1991", "authors": "Hong Xie,W. Allegretto", "jconf": "SIAM Journal on Mathematical Analysis", "id": "1669076", "label": "6", "organization": "null"}, {"title": "State digital library usability: contributing organizational factors", "year": "2002", "authors": "Hong Xie,Dietmar Wolfram", "jconf": "Journal of the American Society for Information Science and Technology", "id": "1705165", "label": "4", "organization": "School of Information Studies, University of Wisconsin-Milwaukee, P.O. Box 413, Milwaukee, WI"}, {"title": "L2,mgr;(OHgr;) estimate to the mixed boundary value problem for second order elliptic equations and its application in the thermistor problem", "year": "1995", "authors": "Hong Xie", "jconf": "Nonlinear Analysis: Theory, Methods Applications", "id": "1713389", "label": "6", "organization": "null"}]}}